data_platfrom_deployer-1.2.0.dist-info/licenses/LICENSE
dpd/__init__.py
dpd/main.py
dpd/models.py
dpd/schema.json
dpd/validation.py
dpd/enums/__init__.py
dpd/enums/service_type.py
dpd/generation/__init__.py
dpd/generation/data_platform.py
dpd/generation/port_manager.py
dpd/generation/secret.py
dpd/services/__init__.py
dpd/services/clickhouse/__init__.py
dpd/services/clickhouse/clickhouse.py
dpd/services/docs/readme.py
dpd/services/kafka/kafka.py
dpd/services/kafka_connect/api.py
dpd/services/kafka_connect/kafka_connect.py
dpd/services/kafka_connect/plugins.py
dpd/services/kafka_ui/kafka_ui.py
dpd/services/minio/minio.py
dpd/services/postgresql/postgresql.conf
dpd/services/postgresql/postgresql.py
dpd/services/superset/superset.py
data_platfrom_deployer-1.2.0.dist-info/METADATA
data_platfrom_deployer-1.2.0.dist-info/WHEEL
data_platfrom_deployer-1.2.0.dist-info/entry_points.txt
data_platfrom_deployer-1.2.0.dist-info/top_level.txt
data_platfrom_deployer-1.2.0.dist-info/RECORD
